file_organizer/__init__.py
file_organizer/core/__init__.py
file_organizer/core/organizer.py
file_organizer/utils/__init__.py
file_organizer/utils/file_utils.py
file_organizer_automation-0.1.0.dist-info/licenses/LICENSE
file_organizer_automation-0.1.0.dist-info/METADATA
file_organizer_automation-0.1.0.dist-info/WHEEL
file_organizer_automation-0.1.0.dist-info/entry_points.txt
file_organizer_automation-0.1.0.dist-info/top_level.txt
file_organizer_automation-0.1.0.dist-info/RECORD
