Metadata-Version: 2.4
Name: file_organizer_automation
Version: 0.1.0
Summary: A tool for organizing files automatically
Home-page: https://github.com/splunkdevabhi/file_organizer_automation
Author: Abhishek Shukla
Author-email: splunkdevabhi@github.com
Project-URL: Bug Tracker, https://github.com/splunkdevabhi/file_organizer_automation/issues
Project-URL: Documentation, https://github.com/splunkdevabhi/file_organizer_automation
Project-URL: Source Code, https://github.com/splunkdevabhi/file_organizer_automation
Keywords: file organization,automation,directory management
Classifier: Programming Language :: Python :: 3
Classifier: License :: OSI Approved :: MIT License
Classifier: Operating System :: OS Independent
Requires-Python: >=3.6
License-File: LICENSE
Requires-Dist: click>=7.0
Requires-Dist: watchdog>=2.0.0
Requires-Dist: colorlog>=6.0.0
Dynamic: author
Dynamic: author-email
Dynamic: classifier
Dynamic: description
Dynamic: description-content-type
Dynamic: home-page
Dynamic: keywords
Dynamic: license-file
Dynamic: project-url
Dynamic: requires-dist
Dynamic: requires-python
Dynamic: summary
